MANIFEST.in
README.rst
setup.py
getmagnetlink/__init__.py
getmagnetlink/__main__.py
getmagnetlink/getmagnetlink.py
getmagnetlink.egg-info/PKG-INFO
getmagnetlink.egg-info/SOURCES.txt
getmagnetlink.egg-info/dependency_links.txt
getmagnetlink.egg-info/entry_points.txt
getmagnetlink.egg-info/requires.txt
getmagnetlink.egg-info/top_level.txt